zebrafishBlood/__init__.py
zebrafishBlood/classify.py
zebrafishBlood/final.py
zebrafishBlood/imgprocessing.py
zebrafishBlood/output.py
zebrafishBlood/pipeline.py
zebrafishBlood/predict.py
zebrafishblood-0.3.4.dist-info/METADATA
zebrafishblood-0.3.4.dist-info/WHEEL
zebrafishblood-0.3.4.dist-info/top_level.txt
zebrafishblood-0.3.4.dist-info/RECORD
