Metadata-Version: 2.1
Name: zebrafishblood
Version: 0.3.4
Summary: Zebrafish blood smear cell counter
Author: ['Eunhye Yang']
Author-email: eunhye@connect.hku.hk
Requires-Dist: scikit-build
Requires-Dist: torch
Requires-Dist: torchvision
Requires-Dist: numpy
Requires-Dist: ultralytics
Requires-Dist: opencv-python
Requires-Dist: openslide-python ==1.3.1
Requires-Dist: joblib
